{
	"achromatopsia_onoff": true,
	"achromatopsia_int": 100,
	"achromatopsia_blur_factor": 0.25,
	"cataract_onoff": false,
	"cataract_int": 0,
	"colorblindness_onoff": false,
	"colorblindness_type": 0,
	"colorblindness_int": 0,
	"glaucoma_onoff": false,
	"glaucoma_fov": 0,
	"maculardegeneration_onoff": false,
	"maculardegeneration_vadvanced": false,
	"maculardegeneration_veasy": false,
	"maculardegeneration_intadvanced": 0,
	"maculardegeneration_inteasy": 0,
	"maculardegeneration_radius": 0,
	"myopiahyperopia_onoff": false,
	"myopiahyperopia_mnh": 50,
	"nyctalopia_onoff": false,
	"nyctalopia_int": 0,
	"presbyopia_onoff": false,
	"presbyopia_near_point": 0,	
	"retina_map_pos_x_path" : null,
	"retina_map_neg_x_path" : null,
	"retina_map_pos_y_path" : null,
	"retina_map_neg_y_path" : null,
	"retina_map_pos_z_path" : null,
	"retina_map_neg_z_path" : null,
	"eye_distance_center": 10,
	"eye_axis_rot_x": 0,
	"eye_axis_rot_y": 0,
	"astigmatism_dpt": 0,
	"astigmatism_angle_deg": 0
}
